{
    "1": [
        {
            "address": "0x155ff1a85f440ee0a382ea949f24ce4e0b751c65",
            "image": "eye",
            "friendlyName": "Eye",
            "category": "Behodler",
            "AMMs": [
                {
                    "location": "uni",
                    "type": "base",
                    "url": "#/swap?inputCurrency=ETH&outputCurrency=0x155ff1a85f440ee0a382ea949f24ce4e0b751c65"
                }
            ]
        },
        {
            "address": "0x1b8568fbb47708e9e9d31ff303254f748805bf21",
            "image": "scx",
            "friendlyName": "Scarcity",
            "category": "Behodler",
            "AMMs": [
                {
                    "location": "behodler",
                    "type": "base",
                    "url": "https://app.behodler.io/"
                },
                {
                    "location": "uni",
                    "type": "base",
                    "url": "#/swap?inputCurrency=ETH&outputCurrency=0x1b8568fbb47708e9e9d31ff303254f748805bf21"
                }
            ]
        },
        {
            "address": "0xc02aaa39b223fe8d0a0e5c4f27ead9083c756cc2",
            "image": "eth",
            "category": "BlueChip",
            "friendlyName": "Ether"
        },
        {
            "address": "0xf047ee812b21050186f86106f6cabdfec35366c6",
            "image": "scxEye",
            "friendlyName": "SCX/EYE LP (Uni-V2)",
            "category": "LP",
            "AMMs": [
                {
                    "location": "uni",
                    "type": "LP",
                    "url": "add/v2/0x155ff1a85f440ee0a382ea949f24ce4e0b751c65/0x1b8568fbb47708e9e9d31ff303254f748805bf21"
                }
            ]
        },
        {
            "address": "0x0287120f9b7d8709b4dd5b589ae759f79fd34e62",
            "image": "pyroScxEye",
            "friendlyName": "Pyro(SCX/EYE)",
            "category": "PyroToken",
            "AMMs": [
                {
                    "location": "behodler",
                    "type": "pyro",
                    "url": "https://app.behodler.io/"
                }
            ]
        },
        {
            "address": "0x319ead06eb01e808c80c7eb9bd77c5d8d163addb",
            "image": "scxEth",
            "friendlyName": "SCX/ETH LP (Uni-V2)",
            "category": "LP",
            "AMMs": [
                {
                    "location": "uni",
                    "type": "LP",
                    "url": "add/v2/ETH/0x1b8568fbb47708e9e9d31ff303254f748805bf21"
                }
            ]
        },
        {
            "address": "0xa9eea8723fffd923f6908586455411159b525d23",
            "image": "pyroScxEth",
            "friendlyName": "Pyro (SCX/ETH)",
            "category": "PyroToken",
            "AMMs": [
                {
                    "location": "behodler",
                    "type": "pyro",
                    "url": "https://app.behodler.io/"
                }
            ]
        },
        {
            "address": "0x1f9840a85d5af5bf1d1762f925bdaddc4201f984",
            "image": "uni",
            "category": "Governance",
            "friendlyName": "Uni",
            "AMMs": [
                {
                    "location": "uni",
                    "type": "base",
                    "url": "#/swap?inputCurrency=ETH&outputCurrency=0x1f9840a85d5af5bf1d1762f925bdaddc4201f984"
                }
            ]
        },
        {
            "address": "0x95ad61b0a150d79219dcf64e1e6cc01f0b64c4ce",
            "image": "shiba",
            "category": "Meme",
            "friendlyName": "Shib",
            "AMMs": [
                {
                    "location": "shiba",
                    "type": "base",
                    "url": "swap?inputCurrency=ETH&outputCurrency=0x95ad61b0a150d79219dcf64e1e6cc01f0b64c4ce"
                },
                {
                    "location": "uni",
                    "type": "base",
                    "url": "swap?inputCurrency=ETH&outputCurrency=0x95ad61b0a150d79219dcf64e1e6cc01f0b64c4ce"
                }
            ]
        }
    ]
    ,
    "31337": [
        {
            "address": "0x1275d096b9dbf2347bd2a131fb6bdab0b4882487",
            "image": "eye",
            "friendlyName": "Eye",
            "category": "Behodler",
            "AMMs": [
                {
                    "location": "uni",
                    "type": "base",
                    "url": "0x0/0x1"
                },
                {
                    "location": "behodler",
                    "type": "base",
                    "url": "https://app.behodler.io/swap"
                }
            ]
        },
        {
            "address": "0x05aa229aec102f78ce0e852a812a388f076aa555",
            "image": "scx",
            "friendlyName": "Scarcity",
            "category": "Behodler",
            "AMMs": [
                {
                    "location": "behodler",
                    "type": "base",
                    "url": "https://app.behodler.io/"
                }
            ]
        },
        {
            "address": "0xdbce93328dc9c9abaea108d25711470fd1875c43",
            "image": "scxEye",
            "friendlyName": "SCX/EYE LP (Uni-V2)",
            "category": "LP",
            "AMMs": [
                {
                    "location": "uni",
                    "type": "LP",
                    "url": "add/v2/0x155ff1A85F440EE0A382eA949f24CE4E0b751c65/0x1B8568FbB47708E9E9D31Ff303254f748805bF21"
                }
            ]
        },
        {
            "address": "0x5c7c905b505f0cf40ab6600d05e677f717916f6b",
            "image": "pyroScxEye",
            "friendlyName": "Pyro (SCX/EYE)",
            "category": "PyroToken",
            "AMMs": [
                {
                    "location": "behodler",
                    "type": "pyro",
                    "url": "https://app.behodler.io/"
                }
            ]
        },
        {
            "address": "0x71c95911e9a5d330f4d621842ec243ee1343292e",
            "image": "eth",
            "category": "BlueChip",
            "friendlyName": "Ether"
        },
        {
            "address": "0xafe1b5bdebd4ae65af2024738bf0735fbb65d44b",
            "image": "shiba",
            "category": "Meme",
            "friendlyName": "Shib",
            "AMMs": [
                {
                    "location": "shiba",
                    "type": "base",
                    "url": "swap?inputCurrency=ETH&outputCurrency=0x95ad61b0a150d79219dcf64e1e6cc01f0b64c4ce"
                }
            ]
        },
        {
            "address": "0x2fc631e4b3018258759c52af169200213e84abab",
            "image": "uni",
            "category": "Governance",
            "friendlyName": "Uni",
            "AMMs": [
                {
                    "location": "uni",
                    "type": "base",
                    "url": "#/swap?inputCurrency=ETH&outputCurrency=0x1f9840a85d5aF5bf1D1762F925BDADdC4201F984"
                }
            ]
        }
    ],
    "11155111": [
        {
            "address": "0xc4171cB917Db366BBcB84aF3472CB63BB0f3a554",
            "image": "eye",
            "friendlyName": "Eye",
            "category": "Behodler",
            "AMMs": [
                {
                    "location": "uni",
                    "type": "base",
                    "url": "#/swap?inputCurrency=ETH&outputCurrency=0x155ff1A85F440EE0A382eA949f24CE4E0b751c65"
                }
            ]
        },
        {
            "address": "0x594d83f99a0339d7FA867F746f8Af91DC4562FC9",
            "image": "scx",
            "friendlyName": "Scarcity",
            "category": "Behodler",
            "AMMs": [
                {
                    "location": "behodler",
                    "type": "base",
                    "url": "https://app.behodler.io/"
                },
                {
                    "location": "uni",
                    "type": "base",
                    "url": "#/swap?inputCurrency=ETH&outputCurrency=0x1b8568fbb47708e9e9d31ff303254f748805bf21"
                }
            ]
        },
        {
            "address": "0xdA479c034876Ee72105a7E536d9077d0b18A68a5",
            "image": "scxEye",
            "friendlyName": "SCX/EYE LP (Uni-V2)",
            "category": "LP",
            "AMMs": [
                {
                    "location": "uni",
                    "type": "LP",
                    "url": "add/v2/0x155ff1A85F440EE0A382eA949f24CE4E0b751c65/0x1B8568FbB47708E9E9D31Ff303254f748805bF21"
                }
            ]
        },
        {
            "address": "0x1070a8B8E83A58856F6a21682868eAf0dc09e6C3",
            "image": "scxEth",
            "friendlyName": "SCX/ETH LP (Uni-V2)",
            "category": "LP",
            "AMMs": [
                {
                    "location": "uni",
                    "type": "LP",
                    "url": "add/v2/ETH/0x1B8568FbB47708E9E9D31Ff303254f748805bF21"
                }
            ]
        }
    ]
}